{"node_external_npm-run-all.md":"72acc327","node_external_npm.md":"a2b3ce6b","node_external_npx.md":"2a9df3cc","node_external_nvm.md":"aca3710a","node_external_package-json.md":"9d873b67","node_external_github.md":"2dd888f6","basic_javascript_object.md":"c9709b5a","node_external_server.md":"cba95eb5","aiart_huggingface_pytorch.md":"51758756","vite_press_vitepress.md":"113f2a06","mac_linux_vim.md":"2e623862","vue_vue3_router-code.md":"f4afbf1c","vue_vue2_defineproperty.md":"5937949f","vue_vue3_pinia-code.md":"14531257","aiart_python_basic-info.md":"42c10559","vite_command-cli.md":"be2ae968","vite_extend_rollup-source-write.md":"22f32ebf","vite_plugin.md":"f3eade8c","vite_press_theme-default.md":"7a9ce329","vite_rollup-source.md":"1dc85874","aiart_comfyui_basic.md":"b39c6557","aiart_python_pil.md":"66e8db80","aiart_python_pip.md":"da7482be","aiart_sunzi-war-art.md":"245f5681","basic_javascript_array.md":"36aa309c","basic_javascript_bitwise-operators.md":"7632cf74","basic_javascript_function.md":"eabd05d9","mac_dev-tools.md":"c2a10ea2","basic_javascript_operators.md":"f385164d","basic_javascript_promise.md":"123c6764","basic_javascript_index.md":"f8dfb596","basic_javascript_reflect.md":"5175ff22","basic_tools_cold-code.md":"04d1fdff","basic_tools_markdown.md":"9398ec4a","basic_tools_worker.md":"3f31caa5","basic_javascript_symbol.md":"eb5054d3","basic_typescript_config-file.md":"7ad05097","basic_typescript_declare.md":"5de639c6","basic_javascript_proxy.md":"921df0b8","basic_typescript_index.md":"e6624774","index.md":"95643711","mathstat_math_number-theory.md":"9ed542b8","mac_daily.md":"f8210f68","basic_typescript_tsx.md":"f85fdd79","node_external_git.md":"26e25cf9","mac_linux_os-command.md":"f9088d66","mac_setting.md":"ba603d61","mathstat_math_calculus.md":"12dbc3fd","mac_vscode.md":"3c16b577","node_core_path.md":"0e5494d8","node_core_http.md":"bfe4ca21","node_core_fs.md":"46ce3d20","mathstat_math_math-symbol.md":"5e9b91e5","node_core_index.md":"bc656496","node_external_cli.md":"7684a879","node_core_process.md":"ec56a356","node_core_url.md":"87ee401a","aiart_machine-learning_overview.md":"10e0f182","aiart_deep-learning_overview.md":"846b2e81","aiart_huggingface_accelerate.md":"538d20e7","aiart_huggingface_config.md":"5e3440a2","vite_rollup.md":"f949c477","aiart_huggingface_diffusers.md":"2ee06dc1","aiart_machine-learning_conda.md":"fb94ce87","vite_index.md":"6cb9e52f","vite_extend_rollup-source-build.md":"f6ab3038","vite_create-vite.md":"dad49579","node_external_websockets.md":"441b37f2","aiart_python_pandas.md":"fae25cd5","vite_press_theme-vue.md":"be261959","vite_press_press-command.md":"5e52c208","node_external_pnpm-monorepo.md":"76d8dd2e","aiart_machine-learning_kaggle.md":"88e01875","aiart_deep-learning_basic-concept.md":"5b766c5c","vue_vue3_reactive.md":"ce8dae98","aiart_python_oop.md":"24e90724","node_external_debug.md":"b5600e72","aiart_chat-gpt.md":"dcbd2557","vue_vue3_source-code.md":"eaaaea5a"}
