{"core_javascript_array.md":"82284e9b","core_javascript_function.md":"3d0beecf","core_typescript_tsx.md":"5c8c5135","node_core_fs.md":"296bea30","core_javascript_index.md":"75ca2c46","node_core_index.md":"08e9b877","node_core_process.md":"03a79b28","core_javascript_operators.md":"77c2ae93","core_javascript_promise.md":"df7aa843","node_external_cli.md":"74b1aee6","core_javascript_symbol.md":"4e8cf97f","vite_command-cli.md":"75b180f9","node_external_pnpm-monorepo.md":"d14f9353","node_external_npm.md":"b10c04d3","node_external_server.md":"af4b97f1","index.md":"e1bd6a59","node_core_url.md":"1f08210b","node_core_path.md":"af29e92f","core_typescript_declare.md":"1387fff2","node_external_debug.md":"2ed5c98a","core_typescript_index.md":"d4fb736a","node_external_npm-run-all.md":"9202a0f0","node_external_npx.md":"111f199f","core_javascript_object.md":"c443fa26","vite_create-vite.md":"b2dc913f","vite_extend_rollup-source-build.md":"28141828","vite_rollup-source.md":"aa25b2e9","vite_rollup.md":"289f5c1a","vite_theme-default.md":"9052b57a","vite_theme-vue.md":"ea12e5ff","vite_vitepress.md":"1fdca7ae","vue_vue2_defineproperty.md":"a3a6f61c","vue_vue3_proxy.md":"cc987dde","vue_vue3_ref.md":"65ebb2c7","vue_vue3_reflect.md":"22aa423d","vue_vue3_source-code.md":"bb980232","node_external_git.md":"95507a20","node_external_github.md":"71ef9df8","core_tools_markdown.md":"8f95c7fc","core_typescript_config-file.md":"06a6f0e6","node_external_nvm.md":"fde5b208","node_core_http.md":"18757ca8","node_external_package-json.md":"be763da5","vite_extend_rollup-source-write.md":"1815581b","vite_index.md":"57e3678f","vite_plugin.md":"ad5bf187"}
